reflex_lasso_select/__init__.py
reflex_lasso_select/lasso_select.py
reflex_lasso_select-0.0.8.dist-info/METADATA
reflex_lasso_select-0.0.8.dist-info/WHEEL
reflex_lasso_select-0.0.8.dist-info/top_level.txt
reflex_lasso_select-0.0.8.dist-info/RECORD
